{"id":{"0":8085032,"1":8178273,"2":8175878,"3":8171364,"4":8027313,"5":8105430,"6":8165405,"7":8162541,"8":8161321,"9":7738157},"companyId":{"0":417,"1":54256,"2":42212,"3":1172,"4":51022,"5":581,"6":54256,"7":808,"8":54256,"9":42212},"name":{"0":"Java Spring Boot Developer for Financial | Mid\/Senior","1":"FullStack Developer especialidad .NET","2":"Developer- Lenguaje Topaz","3":"Mid Mobile Developer - Android (C\/PARC) ","4":"Mobile Developer I Pleno - React Native (Ingl\u00eas) REMOTO","5":"SOFTWARE DEVELOPER S\u00caNIOR - MOBILE FLUTTER | Remoto","6":"Java Developer","7":"[OGI] - Senior .NET Developer ","8":"Java Developer","9":"Sr Developer Analyst"},"description":{"0":".Responsabilidades e atribui\u00e7\u00f5esAtuar no desenvolvimento de projetos que utilizem metodologias \u00e1geis inseridos no contexto de Core Banking Business;Estimular o time a aprimorar a pr\u00e1tica de melhoria cont\u00ednua;Estar constantemente aprendendo, evoluindo e aplicando seus conhecimentos para melhorias nos sistemas e equipes onde atua;Fazer troubleshooting de forma muito r\u00e1pida e eficiente;Colaborar com o time de forma proativa, buscando melhoria tanto no c\u00f3digo fonte como na regra de neg\u00f3cio;Compartilhar conhecimento com os menos experientes;Ter \u201cownership\u201d, expondo suas opini\u00f5es com clareza;Requisitos e qualifica\u00e7\u00f5esLinguagem de programa\u00e7\u00e3o Java (Spring Boot);Git;Mmensageria e filas (Ex: Kafka, SQS, Rabbit MQ);Desenvolvimento de APIs REST;Desenvolvimento de arquitetura distribu\u00edda;Micro servi\u00e7os e ferramentas de orquestra\u00e7\u00e3o (Ex: Kubernetes) e ferramentas de Containers (Ex: Docker);CI\/CD (Ex: Jenkins);Bancos de dados relacionais (Ex: MySQL, Oracle) e n\u00e3o-relacionais (Ex: MongoDB, Cassandra);Testes unit\u00e1rios;Ferramentas e pr\u00e1ticas de monitora\u00e7\u00e3o de sistemas (Ex: New Relic, Grafana, DynaTrace, Splunk);Desenvolvimento utilizando ambiente Linux;Desej\u00e1veis: Spring Cloud, APIs RESTful, Documenta\u00e7\u00e3o de API (Ex: Swagger), Kotlin, SOLID, Design Patterns, atua\u00e7\u00e3o com arquiteturas distribu\u00eddas, resilientes, escal\u00e1veis e de alta performance.N\u00e3o possui todos os requisitos para a vaga?Est\u00e1 tudo bem! Na Compass UOL, estimulamos o desenvolvimento cont\u00ednuo de novos talentos e transformamos desafios em oportunidades.Informa\u00e7\u00f5es adicionais#remote\"remote\"","1":"\u00a1S\u00e9 parte de Stefanini!\u200bEn Stefanini somos m\u00e1s de 30.000 genios, conectados desde 41 pa\u00edses, haciendo lo que les apasiona y co-creando un futuro mejor.\u200bBuscamos un desarrollador full stack altamente capacitado con especializaci\u00f3n en tecnolog\u00eda .NET y SQL Server. El candidato ideal tendr\u00e1 experiencia en el desarrollo y mantenimiento de aplicaciones web, as\u00ed como un s\u00f3lido conocimiento de pr\u00e1cticas de seguridad y herramientas de pruebas.&nbsp;Responsabilidades y atribucionesResponsabilidades:Desarrollar y mantener aplicaciones web utilizando marcos y lenguajes de programaci\u00f3n modernos.Colaborar con dise\u00f1adores, gerentes de producto y otras partes interesadas para recopilar requisitos y traducirlos en especificaciones t\u00e9cnicas.Dise\u00f1ar e implementar interfaces y experiencias f\u00e1ciles de usar.Escriba c\u00f3digo limpio, eficiente y mantenibleRealizar pruebas y depuraciones exhaustivas para garantizar la calidad y confiabilidad de las aplicaciones de software.Solucionar y resolver problemas informados por los usuarios o identificados durante las pruebas.Mant\u00e9ngase actualizado con las tendencias de la industria y las mejores pr\u00e1cticas en desarrollo web.Participar en revisiones de c\u00f3digo para garantizar el cumplimiento de los est\u00e1ndares de codificaci\u00f3n y las mejores pr\u00e1cticas.Colaborar con equipos multifuncionales para garantizar la entrega exitosa de proyectos.Contribuir a la mejora continua de los procesos y herramientas de desarrollo.Requisitos y calificacionesImportante contar con:Requisitos T\u00e9cnicos:&nbsp;Dominio en .NET: Amplia experiencia en el desarrollo de aplicaciones utilizando .NET Framework\/Core, con habilidades para crear soluciones robustas y escalables.&nbsp;Base de Datos SQL Server: Capacidad para dise\u00f1ar e implementar bases de datos relacionales, escribir consultas complejas y desarrollar stored procedures eficientes.&nbsp;Control de Versiones e Integraci\u00f3n con Git: Experiencia en la gesti\u00f3n de c\u00f3digo fuente y colaboraciones de equipo a trav\u00e9s de Git.&nbsp;Revisi\u00f3n de C\u00f3digo: Experiencia en revisiones de c\u00f3digo entre pares para asegurar la calidad y adherencia a buenas pr\u00e1cticas.&nbsp;Diagn\u00f3stico de Aplicaciones: Habilidad para identificar y solucionar problemas de rendimiento y lentitud en aplicaciones.&nbsp;Pruebas de Software: Experiencia en pruebas de integraci\u00f3n, regresi\u00f3n y rendimiento utilizando herramientas como JMeter, Postman, SoapUI, Gatling o similares.&nbsp;Cloud y DevOps: Familiaridad con Azure y sus servicios para integrar soluciones en la nube.&nbsp;Integraci\u00f3n y Consultas a Bases de Datos: Experiencia en la integraci\u00f3n de aplicaciones con bases de datos y la optimizaci\u00f3n de queries.&nbsp;Habilidades Adicionales:&nbsp;Buenas Pr\u00e1cticas de Desarrollo: Compromiso con la implementaci\u00f3n de est\u00e1ndares de codificaci\u00f3n y pr\u00e1cticas \u00e1giles.&nbsp;Experiencia b\u00e1sica CyberSeguridad: Conocimiento del OWASP Top Ten, CWE (Common Weakness Enumeration), y CVE (Common Vulnerabilities and Exposures) para asegurar aplicaciones seguras.&nbsp;Comunicaci\u00f3n y Colaboraci\u00f3n: Habilidad para trabajar en equipo y comunicarse efectivamente con otros desarrolladores y partes interesadas.Informaciones adicionales","2":"En Topaz nos une la tecnolog\u00eda y nos conecta la evoluci\u00f3n!\ud83d\ude80En nuestra organizaci\u00f3n estamos totalmente comprometidos en contribuir a las soluciones financieras que hagan de la industria un lugar seguro, accesible y din\u00e1mico. Queremos llegar a diferentes partes del mundo con nuestro amplio ecosistema de soluciones tecnol\u00f3gicas. \u00a1As\u00ed que te invitamos a que seas parte de este equipo!\ud83d\ude0e\u00a1Adem\u00e1s tenemos grandes beneficios para ti! Sabemos que en conjuntoalcanzaremos el \u00e9xito, as\u00ed que post\u00falate y haz parte de este gran Team.Al integrarte a nuestro&nbsp;Digital Applications&nbsp;Team&nbsp;como&nbsp;Developer&nbsp;&nbsp;tu misi\u00f3n ser\u00e1&nbsp;proporcionar el desarrollo de la mejor experiencia posible de nuestros productos y soluciones de forma accesible para todos nuestros clientes, \u00a1siendo verdadero protagonista de \u00e9xito!&nbsp;Responsabilidades e atribui\u00e7\u00f5esTu d\u00eda a d\u00eda en Topaz \ufeffDesarroll\u00e1s de proyectos de implantaci\u00f3n y desarrollo evolutivo, en los tiempos y niveles de calidad establecidos, utilizando el lenguaje de alto nivel (4GL) de programaci\u00f3n propio de la compa\u00f1\u00eda (Topaz)&nbsp;Adquirir\u00e1s conocimiento funcional del negocio financiero&nbsp;Programar\u00e1s utilizando herramientas tales como Jasper y Kettle&nbsp;Realizar\u00e0s consultas y programaci\u00f3n en base de datos SQL (store procedures, package, vistas)&nbsp;Ser\u00e0s consultor ante el cliente, plantear soluciones a clientes&nbsp;Realizar\u00e1s el an\u00e1lisis de performance&nbsp;&nbsp;Interactuar\u00e1s con diferentes sistemas operativos, sistemas de comunicaci\u00f3n, sistemas de redes, sistemas de canales.&nbsp;Requisitos e qualifica\u00e7\u00f5es\u00bfQu\u00e9 necesitas para ser parte de Topaz? Ser&nbsp;profesional o estudiante de carreras de Analista Programador, de Sistemas,&nbsp;Licenciatura de Sistemas o similar.&nbsp;Poseer conocimiento avanzado de bases de datos SQL (excluyente).&nbsp;Tener experiencia de al menos 1 a\u00f1o en tareas de desarrollo (Deseable)Se valorar\u00e1 tener conocimientos contables y experiencia en el sector financiero.&nbsp;Portugu\u00e9s y\/o ingl\u00e9s (deseable).&nbsp;Capacidad anal\u00edtica, proactividad, orientaci\u00f3n al cliente y trabajo en equipo.&nbsp;&nbsp;Disponibilidad para viajar al exterior espor\u00e1dicamente.&nbsp;Informa\u00e7\u00f5es adicionais\u00a1Ten en cuenta estos beneficios que mejorar\u00e1n tu experiencia en Topaz! Salud y Bienestar: Porque pensamos en nuestros equipos, contamos condiferentes planes de salud, los cuales est\u00e1n enfocados en promover elbienestar en la organizaci\u00f3n.Desarrollo personal y profesional: Estamos en constante evoluci\u00f3n. Poresto, ofrecemos entornos, programas y pol\u00edticas que garantizan el espacio ylas oportunidades necesarias para ti \ud83c\udf93Plan carrera.Modalidad H\u00edbrida: Aqu\u00ed encontrar\u00e1s el tiempo que necesitaspara recargar energ\u00edas, adem\u00e1s podr\u00e1s disfrutar de un d\u00eda libre entu cumplea\u00f1os \ud83e\udd73Modalidad de trabajo h\u00edbrido.Convenios: Ofrecemos diferentes convenios y descuentos.","3":"Aproxime-se. A Invillia n\u00e3o apenas transformou a forma como as empresas mais revolucion\u00e1rias do mundo criam e desenvolvem estrat\u00e9gias, neg\u00f3cios e produtos digitais.Inovou tamb\u00e9m a maneira como pessoas apaixonadas por tecnologia, de qualquer lugar do planeta, podem interagir, evoluir, mais conectados do que nunca.Para a Invillia, n\u00e3o importa onde voc\u00ea est\u00e1. Se \u00e9 um pa\u00eds grande. Ou uma cidade pequena. E sim a sua vontade. As suas ideias. O seu potencial.O tamanho do seu talento_O tamanho do seu talento_Responsabilidades e atribui\u00e7\u00f5es\u00b7&nbsp;&nbsp;&nbsp;&nbsp;&nbsp;&nbsp;Desenvolvimento e manuten\u00e7\u00e3o de aplicativos Mobile;\u00b7&nbsp;&nbsp;&nbsp;&nbsp;&nbsp;&nbsp;Desenvolvimento utilizando metodologias \u00e1geis;\u00b7&nbsp;&nbsp;&nbsp;&nbsp;&nbsp;&nbsp;Desenvolver c\u00f3digo aplicando boas pr\u00e1ticas de desenvolvimento, atrav\u00e9s de documenta\u00e7\u00e3o e hist\u00f3rias de usu\u00e1rio;\u00b7&nbsp;&nbsp;&nbsp;&nbsp;&nbsp;&nbsp;Atuar em corre\u00e7\u00f5es e execu\u00e7\u00f5es de testes.Requisitos e qualifica\u00e7\u00f5es\u00b7&nbsp;&nbsp;&nbsp;&nbsp;&nbsp;&nbsp;Experi\u00eancia com desenvolvimento Android (Nativo);\u00b7&nbsp;&nbsp;&nbsp;&nbsp;&nbsp;&nbsp;Experi\u00eancia com Git e Git Flow;\u00b7&nbsp;&nbsp;&nbsp;&nbsp;&nbsp;&nbsp;Amplos conhecimentos em Java e Kotlin;\u00b7&nbsp;&nbsp;&nbsp;&nbsp;&nbsp;&nbsp;Conhecimento e viv\u00eancia com RESTFul;\u00b7&nbsp;&nbsp;&nbsp;&nbsp;&nbsp;&nbsp;Testes de interface e testes unit\u00e1rios.\u00b7&nbsp;&nbsp;&nbsp;&nbsp;&nbsp;&nbsp;Android Jetpack Components (ViewModel, Room, LiveData, Databinding, Navigation);\u00b7&nbsp;&nbsp;&nbsp;&nbsp;&nbsp;&nbsp;Conhecimento em UI customizada;\u00b7&nbsp;&nbsp;&nbsp;&nbsp;&nbsp;&nbsp;Conhecimento em arquiteturas m\u00f3veis como MVP e MVVM;\u00b7&nbsp;&nbsp;&nbsp;&nbsp;&nbsp;&nbsp;Capacidade de trabalhar em times multidisciplinares e de se comunicar claramente com times de desenvolvimento, design, marketing e produtos;Informa\u00e7\u00f5es adicionaisA experi\u00eancia de trabalhar na Invillia \u00e9 \u00fanica. E global. Temos o nosso pr\u00f3prio jeito de conectar talentos e construir inova\u00e7\u00f5es.Revolucionamos o ambiente de trabalho #Instation + somos experts em desenvolver solu\u00e7\u00f5es complexas para #GameChangers + temos uma metodologia \u00fanica #EngagedbyDataPeopleAction + investimos em pessoas #InvilliaAcademyAlguns diferenciais Invillia:_inovamos lado-a-lado com #GameChangersGlobais_cultura de trabalho distribu\u00eddo #inStation_metodologia exclusiva #GlobalGrowthFramework_benef\u00edcios \u00fanicos entre as techs #InfinitePowersFa\u00e7a uma imers\u00e3o aqui&nbsp;https:\/\/invillia.com\/Ent\u00e3o, se voc\u00ea busca uma oportunidade de trabalhar de onde estiver, em uma empresa dedicada em recriar a sensa\u00e7\u00e3o de proximidade, de conex\u00e3o humana, e de se sentir acolhido a qualquer momento, mesmo com todos distribu\u00eddos, aqui \u00e9 o lugar certo.","4":"We are a reference in implementing digital businesses across Latin America and Europe.As one of the largest companies in this niche, we are recognized for our excellence and are currently positioned as the most valuable agency (MVP) in the Vtex Quadrant.With operations in Brazil, Mexico, Chile, Argentina, and Spain, we serve over 40 countries, partnering with the largest market-leading brands to provide services in e-commerce development, implementation, and evolution, as well as SEO, Media, CRO, and CRM.We have grown significantly and continue to expand, taking on increasingly larger and more complex projects while venturing into international markets. As part of this journey, we were acquired by WPP, the world\u2019s largest communication group.Today, our team consists of over 600 bold, determined, innovative, agile, and collaborative individuals who lead and shape the future of e-commerce together. Join us in building this future #JoinCorebiz.Responsabilidades e atribui\u00e7\u00f5esThe Software Developer\/Programmer is responsible for programming, writing, testing, and maintaining a program. They rely on the requirements gathering and analyses conducted by the systems analyst.Requisitos e qualifica\u00e7\u00f5esDeep understanding of the programming\/functional aspects of native Android and iOS devices.Work with the VTEX platform and its provided APIs.Understand and apply UI animations.Capable of sharing knowledge and assisting other developers with tasks.Skills in reading code, identifying bugs, and proposing improvements.Familiarity with and application of best practices in architecture and coding standards (clean code).Knowledge of the App Store and Play Store.Experience with deployment strategies for app stores.Understanding of programming paradigms, their benefits, and when to use them.Collaborate with third parties responsible for push notifications and event generation for analytics purposes.Work with API strategies such as REST and GraphQL.Differentials:Bachelor's Degree CompletedInforma\u00e7\u00f5es adicionais","5":"LOCALIZA&amp;COEstar em constante evolu\u00e7\u00e3o nos trouxe at\u00e9 aqui. Ao lado de talentos e habilidades m\u00faltiplas nos conectamos em busca da nossa motiva\u00e7\u00e3o: construir o futuro da mobilidade sustent\u00e1vel. \u00c9 por meio da valoriza\u00e7\u00e3o da individualidade de cada um que impulsionamos o nosso movimento para conquistar resultados extraordin\u00e1rios, desenvolver nossas opera\u00e7\u00f5es e criar solu\u00e7\u00f5es para os nossos clientes.Somos apaixonados por nossa hist\u00f3ria, por nossas ideias e pela capacidade de realiz\u00e1-las. Sabemos que juntos, todos vamos mais longe.\u00c9 assim que conectamos a Localiza&amp;Co com o futuro.O QUE VOC\u00ca IR\u00c1 FAZER COMO SOFTWARE DEVELOPER SENIOR:Estamos em busca de um(a) profissional para atuar no desenvolvimento de aplica\u00e7\u00f5es mobile utilizando o framework Flutter. Se voc\u00ea \u00e9 apaixonado por desenvolvimentos de aplicativos m\u00f3veis e est\u00e1 em busca de novos desafios, n\u00f3s adorar\u00edamos conhece-lo(a).&nbsp;Em nosso ambiente de trabalho, utilizamos uma variedade de tecnologias, incluindo:&nbsp;Flutter\/Dart: Um dos frameworks utilizados dentro da Localiza para desenvolvimento de aplica\u00e7\u00f5es mobile.Firebase: Uma das diversas ferramentas que utilizamos que cont\u00e9m diversas solu\u00e7\u00f5es voltadas para o contexto mobile.Azure DevOps: Nossa escolha para solu\u00e7\u00f5es de gerenciamento de projetos e times.GitHub Copilot: Um assistente de programa\u00e7\u00e3o baseado em intelig\u00eancia artificial (IA) que nos ajuda no desenvolvimento.N\u00e3o se preocupe, incentivamos a curiosidade e a busca constante por conhecimento!Responsabilidades e atribui\u00e7\u00f5esLiderar iniciativas de desenvolvimento e implementa\u00e7\u00e3o de novas funcionalidades.Trabalhar em conjunto com a equipe para garantir a qualidade, disponibilidade e seguran\u00e7a do aplicativo.Projetar e implementar arquiteturas e padr\u00f5es de projetos ligados ao desenvolvimento Mobile\/Flutter.Otimizar o desempenho do aplicativo e resolver problemas complexos de forma eficiente e inovadora.Dar suporte a equipe de desenvolvimento e orientar outros desenvolvedores quando necess\u00e1rio.Participar de reuni\u00f5es de planejamento, cerim\u00f4nias de forma ativa do projeto e revis\u00e3o de c\u00f3digo.Configurar pipelines de CI\/CD para automa\u00e7\u00e3o de compila\u00e7\u00e3o, testes e implanta\u00e7\u00e3o quando necess\u00e1rio.Requisitos e qualifica\u00e7\u00f5esExperi\u00eancia com arquiteturas de softwares, padr\u00f5es de projetos ligados ao desenvolvimento mobile e Flutter.Familiaridade com frameworks de inje\u00e7\u00e3o de depend\u00eancia que facilitam a manuten\u00e7\u00e3o e teste de c\u00f3digo.Experi\u00eancia em escrever testes unit\u00e1rios, interface e de instrumenta\u00e7\u00e3o para garantir a qualidade e a confiabilidade do c\u00f3digo.Habilidade para otimizar o desempenho do aplicativo, incluindo o uso eficiente de recursos, gest\u00e3o de mem\u00f3ria e an\u00e1lise de desempenho.Experi\u00eancia em gerenciar o estado da aplica\u00e7\u00e3o de maneira eficiente, possivelmente usando bibliotecas como Bloc, Cubit, MobX ou similares.Experiencia em pr\u00e1ticas de observabilidade para garantir o funcionamento correto da aplica\u00e7\u00e3o.Conhecimento sobre integra\u00e7\u00e3o e comunica\u00e7\u00e3o entre m\u00f3dulos Flutter e aplica\u00e7\u00f5es nativas (Android e iOS)Experi\u00eancia em configurar pipelines de CI\/CD para automa\u00e7\u00e3o de compila\u00e7\u00e3o, testes e implanta\u00e7\u00e3o.Conhecimento do funcionamento das lojas de aplicativos (Google Play e App Store)Informa\u00e7\u00f5es adicionaisBENEF\u00cdCIOS DESSA POSI\u00c7\u00c3OParticipa\u00e7\u00e3o nos Lucros;Carro Corporativo;Vale Alimenta\u00e7\u00e3o;Vale Refei\u00e7\u00e3o;Conv\u00eanio M\u00e9dico;Conv\u00eanio Odontol\u00f3gico;Wellhub;Previd\u00eancia Privada;Allya;Acesso ilimitado a diversos cursos da nossa Universidade Localiza;Programas internos de treinamento e desenvolvimento;Desconto em compra e aluguel de ve\u00edculos.Viva a experi\u00eancia de ser Localiza&amp;Co e venha construir o futuro da mobilidade conosco!","6":"\u00a1S\u00e9 parte de Stefanini!En Stefanini&nbsp;somos m\u00e1s de 30,000 genios, conectados desde 41 pa\u00edses, co-creando un futuro mejor.\u00a1S\u00e9 nuestro Desarrollador JAVA!Responsabilidades y atribuciones1 a\u00f1o de experiencia como Desarrollador Java.Conocimiento en entornos bancarios (deseable).Control, seguimiento y desarrollo completo de los requerimientos del cliente, desde el an\u00e1lisis, dise\u00f1o, construcci\u00f3n, pruebas y liberaci\u00f3n.Requisitos y calificacionesProactivoAutodidactaJAVA EECI\/CDBitbucket\/GITJenkinsSonarQubeCheckMarxJUNITERAJSPLinuxInformaciones adicionales","7":"Senior .NET DeveloperWe are looking for Senior .NET developers who want to work with us in a relaxed and exciting environment, with daily learning opportunities in the development of large projects for major clients worldwide. Our office is located in Chicago, USA, but we operate remotely; we prefer to call it an anywhere office.*Requirements:*- Previous experience with .NET Framework and .NET Core, React, and Angular- Great development practices- Knowledge of databases (SQL Server stored procedures)- Advanced English*Nice to have:*- Understanding of microservices communication and messaging systems_____________________________________Desenvolvedor .Net PlenoBuscamos devs .Net, em n\u00edveis de carreira Senior, que queiram trabalhar conosco em um ambiente descontra\u00eddo e animado, com aprendizado di\u00e1rio no desenvolvimento de grandes projetos, junto a grandes clientes pelo mundo. Nosso escrit\u00f3rio \u00e9 em Chicago (EUA), mas a nossa atua\u00e7\u00e3o \u00e9 remota: por aqui preferimos chamar de anywhere office.- Experi\u00eancia anterior com .Net e core, react e angular- \u00d3timas pr\u00e1ticas de desenvolvimento- Conhecimento em banco de dados (stored procedures de sql server)- Ingl\u00eas avan\u00e7ado*Seria um diferencial*Conhecimento em XamarinSaber sobre comunica\u00e7\u00e3o entre micro servi\u00e7os e mensageriaResponsabilidades e atribui\u00e7\u00f5esRequisitos e qualifica\u00e7\u00f5esInforma\u00e7\u00f5es adicionais","8":"\u00a1S\u00e9 parte de Stefanini!En Stefanini&nbsp;somos m\u00e1s de 30,000 genios, conectados desde 41 pa\u00edses, co-creando un futuro mejor.\u00a1S\u00e9 nuestro Desarrollador JAVA!Responsabilidades y atribuciones1 a 2 a\u00f1os de experiencia como Desarrollador JavaConocimiento en entornos bancarios (deseable)Control, seguimiento y desarrollo completo de los requerimientos del cliente, desde el an\u00e1lisis, dise\u00f1o, construcci\u00f3n, pruebas y liberaci\u00f3n&nbsp;Requisitos y calificacionesProactivoAutodidactaJAVA EECI\/CDBitbucket\/GITJenkinsSonarQubeCheckMarxJUNITERAJSPLinuxInformaciones adicionales","9":"Na Topaz, a tecnologia nos une e a evolu\u00e7\u00e3o nos conecta! \ud83d\ude80Em nossa organiza\u00e7\u00e3o, estamos totalmente comprometidos em contribuir para solu\u00e7\u00f5es financeiras que tornem a ind\u00fastria um lugar seguro, acess\u00edvel e din\u00e2mico. Queremos alcan\u00e7ar diferentes partes do mundo com nosso amplo ecossistema de solu\u00e7\u00f5es tecnol\u00f3gicas. Por isso, convidamos voc\u00ea a fazer parte dessa equipe! \ud83d\ude0eAl\u00e9m disso, temos \u00f3timos benef\u00edcios para voc\u00ea! Sabemos que, juntos, alcan\u00e7aremos o sucesso, ent\u00e3o se candidate e fa\u00e7a parte desse grande time.Responsabilidades e atribui\u00e7\u00f5esSeu dia a dia na&nbsp;Topaz:Atuar no planejamento e desenvolvimento dos produtos com o olhar voltado \u00e0 qualidade;Trabalhar em conjunto com times de diferentes \u00e1reas observando as melhores pr\u00e1ticas de desenvolvimento;Efetuar testes explorat\u00f3rios do que \u00e9 desenvolvido e oferecer feedback e sugest\u00f5es aos times;Automatizar testes dos produtos e buscar sempre as melhores pr\u00e1ticas nas etapas de desenvolvimento;Buscar conhecimento nas tecnologias utilizadas e trazer novas ideias ao restante do time.Requisitos e qualifica\u00e7\u00f5esO que voc\u00ea precisa conhecer para ser parte da Topaz?Experi\u00eancia com Python e principais bibliotecas da linguagem;Conhecimento em testes unit\u00e1rios e testes de integra\u00e7\u00e3o;Saber utilizar o GIT;Experi\u00eancia com boas pr\u00e1ticas de programa\u00e7\u00e3o e metodologias \u00e1geis;Conhecimento em arquitetura de software;Conhecimento em integra\u00e7\u00e3o cont\u00ednua;Tomar boas decis\u00f5es de Engenharia de Software com autonomia, considerando vari\u00e1veis t\u00e9cnicas e n\u00e3o t\u00e9cnicas;Boa comunica\u00e7\u00e3o, pois ir\u00e1 trabalhar em um time onde a comunica\u00e7\u00e3o \u00e9 fundamental;A equipe est\u00e1 em crescimento e facilidade de adapta\u00e7\u00e3o a novos desafios \u00e9 muito importante.&nbsp;Diferencial:\ufeffTer atuado ou conhecer BDD e profici\u00eancia em PythonSaber utilizar o GIT.Experi\u00eancia com boas pr\u00e1ticas de programa\u00e7\u00e3o e com metodologias \u00e1geis.Conhecimento em integra\u00e7\u00e3o cont\u00ednua.Experi\u00eancia com plataformas de testes automatizados e testes de unidadeFamiliaridade com integra\u00e7\u00e3o cont\u00ednua.Experi\u00eancia com desenvolvimento Mobile e Web.Espanhol b\u00e1sico.Informa\u00e7\u00f5es adicionaisTenha em mente esses benef\u00edcios que ir\u00e3o melhorar sua experi\u00eancia na Topaz!Sa\u00fade e Bem-estar: Porque pensamos em nossas equipes, oferecemos diferentes planos de sa\u00fade, focados em promover o bem-estar na organiza\u00e7\u00e3o.Desenvolvimento pessoal e profissional: Estamos em constante evolu\u00e7\u00e3o. Por isso, oferecemos ambientes, programas e pol\u00edticas que garantem o espa\u00e7o e as oportunidades necess\u00e1rias para voc\u00ea\ud83c\udf93Rota de carreira.Flexibilidade e tempo livre: Aqui voc\u00ea encontrar\u00e1 o tempo necess\u00e1rio para recarregar as energias, al\u00e9m de poder desfrutar de um dia de folga&nbsp;no seu anivers\u00e1rio\ud83e\udd73 Modalidade de trabalho h\u00edbrido.Conv\u00eanios: Oferecemos diferentes conv\u00eanios e descontos.#VemSerTopaz"},"careerPageId":{"0":35254,"1":114440,"2":89869,"3":1825,"4":105945,"5":679,"6":114440,"7":176930,"8":114440,"9":100035},"careerPageName":{"0":"Compass UOL","1":"STEFANINI LATAM","2":"topazlatam","3":"invillia","4":"Corebiz","5":"Localiza&Co","6":"STEFANINI LATAM","7":"OGI.Systems","8":"STEFANINI LATAM","9":"Topaz Brasil"},"careerPageLogo":{"0":"https:\/\/attachments.gupy.io\/production\/companies\/417\/career\/35254\/images\/2024-11-07_16-21_companyLogoUrl.jpg","1":"https:\/\/attachments.gupy.io\/production\/companies\/54256\/career\/114440\/images\/2022-11-22_20-33_logo.png","2":"https:\/\/attachments.gupy.io\/production\/companies\/42212\/career\/89869\/images\/2024-09-24_15-10_companyLogoUrl.jpg","3":"https:\/\/attachments.gupy.io\/production\/companies\/1172\/career\/1825\/images\/2022-10-14_20-54_logo.png","4":"https:\/\/attachments.gupy.io\/production\/companies\/51022\/career\/105945\/images\/2022-10-18_17-47_logo.png","5":"https:\/\/attachments.gupy.io\/production\/companies\/581\/career\/679\/images\/2023-09-21_21-31_companyLogoUrl.png","6":"https:\/\/attachments.gupy.io\/production\/companies\/54256\/career\/114440\/images\/2022-11-22_20-33_logo.png","7":"https:\/\/attachments.gupy.io\/production\/companies\/808\/career\/176930\/images\/2024-07-08_19-38_companyLogoUrl.jpg","8":"https:\/\/attachments.gupy.io\/production\/companies\/54256\/career\/114440\/images\/2022-11-22_20-33_logo.png","9":"https:\/\/attachments.gupy.io\/production\/companies\/42212\/career\/100035\/images\/2024-09-24_15-31_companyLogoUrl.jpg"},"type":{"0":"vacancy_type_effective","1":"vacancy_type_effective","2":"vacancy_type_effective","3":"vacancy_type_effective","4":"vacancy_type_effective","5":"vacancy_type_effective","6":"vacancy_type_temporary","7":"vacancy_type_effective","8":"vacancy_type_temporary","9":"vacancy_type_effective"},"publishedDate":{"0":"2024-11-22T20:30:16.591Z","1":"2024-11-22T18:45:19.636Z","2":"2024-11-22T15:07:32.789Z","3":"2024-11-22T13:24:28.939Z","4":"2024-11-21T20:21:17.466Z","5":"2024-11-21T12:49:04.627Z","6":"2024-11-20T19:06:19.427Z","7":"2024-11-19T20:52:34.264Z","8":"2024-11-19T20:26:21.349Z","9":"2024-11-19T13:58:58.876Z"},"applicationDeadline":{"0":"2025-01-04T00:00:00.000Z","1":"2025-01-21T00:00:00.000Z","2":"2025-01-31T00:00:00.000Z","3":"2025-01-20T00:00:00.000Z","4":"2024-12-23T00:00:00.000Z","5":"2025-12-15T00:00:00.000Z","6":"2025-01-19T00:00:00.000Z","7":"2025-01-18T00:00:00.000Z","8":"2025-01-18T00:00:00.000Z","9":"2025-01-31T00:00:00.000Z"},"isRemoteWork":{"0":true,"1":true,"2":false,"3":true,"4":true,"5":true,"6":true,"7":true,"8":true,"9":false},"city":{"0":"","1":"","2":"Montevideo","3":"","4":"","5":"","6":"","7":"","8":"","9":"Indaiatuba"},"state":{"0":"","1":"","2":"","3":"","4":"","5":"","6":"","7":"","8":"","9":"S\u00e3o Paulo"},"country":{"0":"Brasil","1":"M\u00e9xico","2":"Uruguai","3":"Brasil","4":"Brasil","5":"Brasil","6":"Peru","7":"Brasil","8":"Peru","9":"Brasil"},"jobUrl":{"0":"https:\/\/compass.gupy.io\/job\/eyJqb2JJZCI6ODA4NTAzMiwic291cmNlIjoiZ3VweV9wb3J0YWwifQ==?jobBoardSource=gupy_portal","1":"https:\/\/stefaninilatam.gupy.io\/job\/eyJqb2JJZCI6ODE3ODI3Mywic291cmNlIjoiZ3VweV9wb3J0YWwifQ==?jobBoardSource=gupy_portal","2":"https:\/\/topaz.gupy.io\/job\/eyJqb2JJZCI6ODE3NTg3OCwic291cmNlIjoiZ3VweV9wb3J0YWwifQ==?jobBoardSource=gupy_portal","3":"https:\/\/invillia.gupy.io\/job\/eyJqb2JJZCI6ODE3MTM2NCwic291cmNlIjoiZ3VweV9wb3J0YWwifQ==?jobBoardSource=gupy_portal","4":"https:\/\/corebiz.gupy.io\/job\/eyJqb2JJZCI6ODAyNzMxMywic291cmNlIjoiZ3VweV9wb3J0YWwifQ==?jobBoardSource=gupy_portal","5":"https:\/\/localiza.gupy.io\/job\/eyJqb2JJZCI6ODEwNTQzMCwic291cmNlIjoiZ3VweV9wb3J0YWwifQ==?jobBoardSource=gupy_portal","6":"https:\/\/stefaninilatam.gupy.io\/job\/eyJqb2JJZCI6ODE2NTQwNSwic291cmNlIjoiZ3VweV9wb3J0YWwifQ==?jobBoardSource=gupy_portal","7":"https:\/\/ogisystems.gupy.io\/job\/eyJqb2JJZCI6ODE2MjU0MSwic291cmNlIjoiZ3VweV9wb3J0YWwifQ==?jobBoardSource=gupy_portal","8":"https:\/\/stefaninilatam.gupy.io\/job\/eyJqb2JJZCI6ODE2MTMyMSwic291cmNlIjoiZ3VweV9wb3J0YWwifQ==?jobBoardSource=gupy_portal","9":"https:\/\/topazbrasil.gupy.io\/job\/eyJqb2JJZCI6NzczODE1Nywic291cmNlIjoiZ3VweV9wb3J0YWwifQ==?jobBoardSource=gupy_portal"},"badges":{"0":{"friendlyBadge":true},"1":{"friendlyBadge":false},"2":{"friendlyBadge":false},"3":{"friendlyBadge":false},"4":{"friendlyBadge":true},"5":{"friendlyBadge":true},"6":{"friendlyBadge":false},"7":{"friendlyBadge":true},"8":{"friendlyBadge":false},"9":{"friendlyBadge":false}},"disabilities":{"0":true,"1":true,"2":true,"3":true,"4":true,"5":true,"6":true,"7":true,"8":true,"9":true},"workplaceType":{"0":"remote","1":"remote","2":"hybrid","3":"remote","4":"remote","5":"remote","6":"remote","7":"remote","8":"remote","9":"hybrid"},"careerPageUrl":{"0":"https:\/\/compass.gupy.io\/eyJzb3VyY2UiOiJndXB5X3BvcnRhbCJ9","1":"https:\/\/stefaninilatam.gupy.io\/eyJzb3VyY2UiOiJndXB5X3BvcnRhbCJ9","2":"https:\/\/topaz.gupy.io\/eyJzb3VyY2UiOiJndXB5X3BvcnRhbCJ9","3":"https:\/\/invillia.gupy.io\/eyJzb3VyY2UiOiJndXB5X3BvcnRhbCJ9","4":"https:\/\/corebiz.gupy.io\/eyJzb3VyY2UiOiJndXB5X3BvcnRhbCJ9","5":"https:\/\/localiza.gupy.io\/eyJzb3VyY2UiOiJndXB5X3BvcnRhbCJ9","6":"https:\/\/stefaninilatam.gupy.io\/eyJzb3VyY2UiOiJndXB5X3BvcnRhbCJ9","7":"https:\/\/ogisystems.gupy.io\/eyJzb3VyY2UiOiJndXB5X3BvcnRhbCJ9","8":"https:\/\/stefaninilatam.gupy.io\/eyJzb3VyY2UiOiJndXB5X3BvcnRhbCJ9","9":"https:\/\/topazbrasil.gupy.io\/eyJzb3VyY2UiOiJndXB5X3BvcnRhbCJ9"}}